setup.py
cerebro/__init__.py
cerebro/admin.py
cerebro/models.py
cerebro/settings.py
cerebro/tests.py
cerebro/urls.py
cerebro/views.py
django_cerebro.egg-info/PKG-INFO
django_cerebro.egg-info/SOURCES.txt
django_cerebro.egg-info/dependency_links.txt
django_cerebro.egg-info/not-zip-safe
django_cerebro.egg-info/requires.txt
django_cerebro.egg-info/top_level.txt