Metadata-Version: 1.0
Name: django-cerebro
Version: 0.0.1
Summary: A django-app that allows a people geolocalisation service
Home-page: http://github.com/sieben/django-cerebro
Author: Rémy Léone
Author-email: remy.leone@gmail.com
License: GNU
Download-URL: http://github.com/sieben/django-cerebro
Platform: UNKNOWN
Classifier: Environment :: Web Environment
Classifier: Intended Audience :: Developers
Classifier: Operating System :: OS Independent
Classifier: Programming Language :: Python
Classifier: Framework :: Django
